<?xml version="1.0"?>
<!--The COPYRIGHT file at the top level of this repository
contains the full copyright notices and license terms. -->
<data>
    <xpath expr="/form/notebook/page[@id='general']/field[@name='update_unit_price']"
        position="after">
        <label name="deducible"/>
        <field name="deducible"/>
        <label name="isp"/>
        <field name="isp"/>
        <label name="service"/>
        <field name="service"/>
        <label name="tax_kind"/>
        <field name="tax_kind"/>
        <label name="recargo_equivalencia_related_tax"/>
        <field name="recargo_equivalencia_related_tax"/>

    </xpath>
    <xpath expr="/form/notebook/page[@id='general']" position="after">
        <page string="Codes" id="code_lines">
            <field name="code_lines" colspan="4"/>
        </page>
   </xpath>
</data>
